{
  "title": "[CODE1-3-09] 海底探险2",
  "source": "C:\\Users\\Frank.J\\starplanet_ai_academy\\知识库\\萃取报告\\CODE\\CODE1\\M3_编程启蒙\\CODE1-3-09_海底探险2.md",
  "sections": [
    {
      "title": "课程基本信息",
      "content": "| 项目 | 内容 |\n|------|------|\n| **课程编号** | 1-3-09 |\n| **课程名称** | 海底探险2 |\n| **认知负荷** | 高 |\n| **核心技能** | 条件判断if-then-else |\n| **项目内容** | 智能躲避游戏 |\n\n---"
    },
    {
      "title": "详细教学流程",
      "content": "### 步骤1：课堂问候（2分钟）\n`#低负荷-热身` `#IFC-预防`\n\n**教师话术**\n> \"小朋友们好！上节课我们学了'如果...那么'，今天我们要学习它的升级版——'如果...那么...否则'！\"\n\n---\n\n### 步骤2：课程回顾（8分钟）\n`#低负荷-热身` `#IFC-预防`\n\n**教师话术**\n> \"谁能告诉我，'如果...那么'是什么意思？（如果条件成立，就执行里面的代码）很好！但是如果条件不成立呢？什么都不做吗？今天我们要学习条件不成立时也能做事情！\"\n\n**变体示例**\n\n| 学生情况 | 调整方案 | 说明 |\n|----------|----------|------|\n| if-then不熟 | 快速复习 | 运行上节课作品回顾 |\n| 掌握很好 | 引入问题 | \"条件不成立时怎么办？\" |\n| 概念混淆 | 生活类比 | \"如果下雨就带伞，否则就不带\" |\n\n---\n\n### 步骤3：情境引入（5分钟）\n`#低负荷-热身` `#IFC-预防`\n\n**教师话术**\n> \"【播放动画】小鱼在海底游泳，如果碰到鲨鱼就要逃跑，否则就继续游泳找食物。这就需要用到'如果...那么...否则'！\"\n\n---\n\n### 步骤4：任务分析（25分钟）\n`#中负荷-操练` `#IFC-即时` ⭐核心环节\n\n**教师话术**\n> \"上节课的'如果...那么'只能处理条件成立的情况。\n>\n> 今天学的'如果...那么...否则'可以处理两种情况：\n> - 如果条件成立，执行'那么'里的代码\n> - 如果条件不成立，执行'否则'里的代码\n>\n> 比如：\n> - 如果（碰到鲨鱼）\n>   - 那么：说'危险！'然后逃跑\n>   - 否则：继续游泳找食物\n>\n> 这就像红绿灯：如果是绿灯就走，否则就停。\"\n\n**变体示例**\n\n| 学生情况 | 调整方案 | 说明 |\n|----------|----------|------|\n| 混淆两种条件 | 对比演示 | 同时展示if-then和if-then-else |\n| 否则部分不理解 | 多举例子 | \"如果饿了就吃饭，否则就玩\" |\n| 理解很快 | 增加复杂度 | \"能不能嵌套多个条件？\" |\n\n**禁忌提醒**\n- ❌ 不要混淆\"如果...那么\"和\"如果...那么...否则\"——后者多了条件不成立的处理\n- ❌ 不要让\"否则\"部分为空——如果不需要否则，就用简单的if-then\n\n---\n\n### 步骤5：编程设计（25分钟）\n`#高负荷-产出` `#IFC-即时`\n\n**教师话术**\n> \"我们来改进海底探险游戏：\n> 1. 当绿旗被点击\n> 2. 重复执行\n>    - 如果（碰到鲨鱼）\n>      - 那么：说'危险！'，移到随机位置\n>      - 否则：面向鼠标指针，移动5步\n>\n> 现在小鱼会自动判断是否遇到危险！\"\n\n**即时反馈检查点**\n- 检查条件判断类型是否正确\n- 检查\"那么\"和\"否则\"的代码是否放对位置\n- 检查逻辑是否符合预期\n\n---\n\n### 步骤6：拓展环节（10分钟）\n`#高负荷-产出` `#IFC-即时`\n\n**教师话术**\n> \"创意挑战：\n> 1. 添加食物，碰到食物加分\n> 2. 让鲨鱼也会移动追小鱼\n> 3. 添加生命值，碰到鲨鱼减一条命\"\n\n---\n\n### 步骤7：家长班会（10分钟）\n`#低负荷-热身` `#IFC-复盘`\n\n**教师话术**\n> \"各位家长，今天孩子们学习了完整的条件判断结构——'如果...那么...否则'。这是编程中最重要的逻辑结构之一，孩子们已经能让程序做出智能决策了！\"\n\n---"
    },
    {
      "title": "核心知识点",
      "content": "- **如果...那么...否则 (If-Then-Else)**：完整的条件分支\n- **二选一逻辑**：条件成立和不成立分别执行不同代码\n- **条件判断对比**：if-then vs if-then-else\n\n---"
    },
    {
      "title": "底层逻辑",
      "content": "- **分支结构**：程序三大结构之一\n- **二元决策**：计算机的基本决策模式\n\n---\n\n`#执行层` `#测评项`\n[UID: CODE1-M3-09-001]\n[关联: CODE1-M3-08-001 上一课]\n[关联: CODE1-M3-10-001 下一课]\n\n---\n\n← [上一课：海底探险](CODE1-3-08_海底探险.md) | [下一课：海底探险3](CODE1-3-10_海底探险3.md) →"
    }
  ],
  "full_content": "# [CODE1-3-09] 海底探险2\n\n> **模块**：M3 编程启蒙\n> **认知负荷**：高\n> **核心技能**：条件判断if-then-else\n> **UID**：CODE1-M3-09-001\n\n---\n\n## 课程基本信息\n\n| 项目 | 内容 |\n|------|------|\n| **课程编号** | 1-3-09 |\n| **课程名称** | 海底探险2 |\n| **认知负荷** | 高 |\n| **核心技能** | 条件判断if-then-else |\n| **项目内容** | 智能躲避游戏 |\n\n---\n\n## 详细教学流程\n\n### 步骤1：课堂问候（2分钟）\n`#低负荷-热身` `#IFC-预防`\n\n**教师话术**\n> \"小朋友们好！上节课我们学了'如果...那么'，今天我们要学习它的升级版——'如果...那么...否则'！\"\n\n---\n\n### 步骤2：课程回顾（8分钟）\n`#低负荷-热身` `#IFC-预防`\n\n**教师话术**\n> \"谁能告诉我，'如果...那么'是什么意思？（如果条件成立，就执行里面的代码）很好！但是如果条件不成立呢？什么都不做吗？今天我们要学习条件不成立时也能做事情！\"\n\n**变体示例**\n\n| 学生情况 | 调整方案 | 说明 |\n|----------|----------|------|\n| if-then不熟 | 快速复习 | 运行上节课作品回顾 |\n| 掌握很好 | 引入问题 | \"条件不成立时怎么办？\" |\n| 概念混淆 | 生活类比 | \"如果下雨就带伞，否则就不带\" |\n\n---\n\n### 步骤3：情境引入（5分钟）\n`#低负荷-热身` `#IFC-预防`\n\n**教师话术**\n> \"【播放动画】小鱼在海底游泳，如果碰到鲨鱼就要逃跑，否则就继续游泳找食物。这就需要用到'如果...那么...否则'！\"\n\n---\n\n### 步骤4：任务分析（25分钟）\n`#中负荷-操练` `#IFC-即时` ⭐核心环节\n\n**教师话术**\n> \"上节课的'如果...那么'只能处理条件成立的情况。\n>\n> 今天学的'如果...那么...否则'可以处理两种情况：\n> - 如果条件成立，执行'那么'里的代码\n> - 如果条件不成立，执行'否则'里的代码\n>\n> 比如：\n> - 如果（碰到鲨鱼）\n>   - 那么：说'危险！'然后逃跑\n>   - 否则：继续游泳找食物\n>\n> 这就像红绿灯：如果是绿灯就走，否则就停。\"\n\n**变体示例**\n\n| 学生情况 | 调整方案 | 说明 |\n|----------|----------|------|\n| 混淆两种条件 | 对比演示 | 同时展示if-then和if-then-else |\n| 否则部分不理解 | 多举例子 | \"如果饿了就吃饭，否则就玩\" |\n| 理解很快 | 增加复杂度 | \"能不能嵌套多个条件？\" |\n\n**禁忌提醒**\n- ❌ 不要混淆\"如果...那么\"和\"如果...那么...否则\"——后者多了条件不成立的处理\n- ❌ 不要让\"否则\"部分为空——如果不需要否则，就用简单的if-then\n\n---\n\n### 步骤5：编程设计（25分钟）\n`#高负荷-产出` `#IFC-即时`\n\n**教师话术**\n> \"我们来改进海底探险游戏：\n> 1. 当绿旗被点击\n> 2. 重复执行\n>    - 如果（碰到鲨鱼）\n>      - 那么：说'危险！'，移到随机位置\n>      - 否则：面向鼠标指针，移动5步\n>\n> 现在小鱼会自动判断是否遇到危险！\"\n\n**即时反馈检查点**\n- 检查条件判断类型是否正确\n- 检查\"那么\"和\"否则\"的代码是否放对位置\n- 检查逻辑是否符合预期\n\n---\n\n### 步骤6：拓展环节（10分钟）\n`#高负荷-产出` `#IFC-即时`\n\n**教师话术**\n> \"创意挑战：\n> 1. 添加食物，碰到食物加分\n> 2. 让鲨鱼也会移动追小鱼\n> 3. 添加生命值，碰到鲨鱼减一条命\"\n\n---\n\n### 步骤7：家长班会（10分钟）\n`#低负荷-热身` `#IFC-复盘`\n\n**教师话术**\n> \"各位家长，今天孩子们学习了完整的条件判断结构——'如果...那么...否则'。这是编程中最重要的逻辑结构之一，孩子们已经能让程序做出智能决策了！\"\n\n---\n\n## 核心知识点\n\n- **如果...那么...否则 (If-Then-Else)**：完整的条件分支\n- **二选一逻辑**：条件成立和不成立分别执行不同代码\n- **条件判断对比**：if-then vs if-then-else\n\n---\n\n## 底层逻辑\n\n- **分支结构**：程序三大结构之一\n- **二元决策**：计算机的基本决策模式\n\n---\n\n`#执行层` `#测评项`\n[UID: CODE1-M3-09-001]\n[关联: CODE1-M3-08-001 上一课]\n[关联: CODE1-M3-10-001 下一课]\n\n---\n\n← [上一课：海底探险](CODE1-3-08_海底探险.md) | [下一课：海底探险3](CODE1-3-10_海底探险3.md) →\n"
}