{
  "title": "PythonAI萃取：L1-1 函数封装与交互",
  "source": "C:\\Users\\Frank.J\\starplanet_ai_academy\\知识库\\萃取报告\\PythonAI\\L1_01_函数封装.md",
  "sections": [
    {
      "title": "单元概览",
      "content": "| 项目 | 内容 |\n|------|------|\n| **单元编号** | PYAI 1-1 |\n| **单元名称** | 函数封装与交互机制 |\n| **适用年龄** | 三年级及以上（8-10岁） |\n| **课时数** | 11节 × 90分钟 |\n| **核心目标** | 从顺序执行转向模块化编程，掌握函数定义与调用 |\n| **主要平台** | CodeCombat |\n\n**底层逻辑**\n掌握函数的定义与调用，并引入人机交互（输入/输出/事件），培养模块化编程思想。\n\n**单元教学策略**\n- 函数基础（01-04）：def定义、参数、多参数\n- 高级概念（05-07）：默认参数、作用域、策略\n- 交互应用（08-11）：input、运算、碰撞检测\n\n`#执行层` `#测评项`\n[UID: PYAI-11-001]\n[关联: PYAI-10-001 PythonAI基础语法（前置基础）]\n[关联: PYAI-12-001 PythonAI算法逻辑（进阶衔接）]\n\n---"
    },
    {
      "title": "课程列表",
      "content": "| 课次 | 课程名称 | 核心知识点 | 项目/关卡 | 认知负荷 |\n|------|----------|------------|-----------|----------|\n| 1-1-1 | 一夫当关 | 函数定义(def)、函数调用、代码复用 | 乡村巡游者 | 中-高 |\n| 1-1-2 | 未雨绸缪 | 形式参数、实际参数、参数类型 | 迷藏 | 高 |\n| 1-1-3 | 棱角分明 | 绘图指令、参数应用、几何逻辑 | 绘制多边形 | 中-高 |\n| 1-1-4 | 对照实验 | 多参数函数、位置参数 | 返回荆棘农场 | 高 |\n| 1-1-5 | 电光火石 | 默认参数、局部变量vs全局变量 | 函数巡逻 | 高 |\n| 1-1-6 | 言听计从1 | 事件监听、pet.on()、hear/spawn事件 | 边地好伙伴 | 高 |\n| 1-1-7 | 棋逢对手 | 策略制定、红蓝对抗 | 竞技场 | 高 |\n| 1-1-8 | 量入为出 | input输入、类型转换、f-string格式化 | 交互式对话 | 中-高 |\n| 1-1-9 | 算术运算 | 算术运算符(//, %, **)、eval()函数 | 简易计算器 | 高 |\n| 1-1-10 | 关系运算 | 比较运算符、布尔值、变量交换 | 变量交换 | 中-高 |\n| 1-1-11 | 碰撞检测 | 碰撞原理、distanceTo、touching | 月食/交通 | 高 |\n\n---"
    },
    {
      "title": "通用教学流程（90分钟）",
      "content": "| 环节 | 时间 | 内容 | 认知负荷 | IFC标签 |\n|------|------|------|----------|---------|\n| 课堂问候 | 2分钟 | 自我介绍、学习目标 | `#低负荷-热身` | `#IFC-预防` |\n| 课程回顾 | 5分钟 | 复习上节课代码知识 | `#低负荷-热身` | `#IFC-预防` |\n| 知识讲解 | 15分钟 | 新语法/概念讲解 | `#中负荷-操练` | `#IFC-即时` |\n| 闯关实践 | 35分钟 | CodeCombat闯关 | `#高负荷-产出` | `#IFC-即时` |\n| 调节休息 | 3分钟 | 站起来活动、眼保健操 | `#调节-放松` | - |\n| 项目创作 | 20分钟 | 综合项目/自由创作 | `#高负荷-产出` | `#IFC-即时` |\n| 成果展示 | 10分钟 | 分享代码、讲解思路 | `#低负荷-热身` | `#IFC-复盘` |\n\n`#执行层` `#测评项`\n[UID: PYAI-11-FLOW-001]\n\n---"
    },
    {
      "title": "详细课程萃取",
      "content": "### 1-1-1 一夫当关（典型案例）\n\n#### 课程基本信息\n\n| 项目 | 内容 |\n|------|------|\n| **课程编号** | 1-1-1 |\n| **课程名称** | 一夫当关 |\n| **认知负荷** | 中-高 |\n| **核心技能** | 函数定义、函数调用、代码复用 |\n\n#### 详细教学流程\n\n**步骤1：知识讲解（15分钟）** `#中负荷-操练` `#IFC-即时`\n\n**教师话术**\n> \"今天我们学习一个超级重要的概念——**函数**！函数就像'打包'代码的工具，把重复的动作装进一个盒子里，需要时拿出来用。\"\n>\n> \"定义函数用 `def` 关键字：\n> ```python\n> def attack_enemy():\n>     enemy = hero.findNearestEnemy()\n>     if enemy:\n>         hero.attack(enemy)\n> ```\n>\n> 调用函数就是喊一声它的名字：\n> ```python\n> attack_enemy()  # 执行攻击函数\n> ```\"\n\n**变体示例**\n\n| 学生情况 | 调整方案 | 说明 |\n|----------|----------|------|\n| 不理解函数用途 | 用遥控器类比 | \"函数就像遥控器按钮，按一下执行一串动作\" |\n| 忘记冒号 | 口诀强化 | \"def后面要冒号，缩进代码不能少\" |\n| 想了解更多 | 介绍内置函数 | print()、len()都是函数 |\n\n---\n\n**步骤2：闯关实践（35分钟）** `#高负荷-产出` `#IFC-即时`\n\n**教师话术**\n> \"现在进入CodeCombat闯关！这一关敌人很多，如果每次都写攻击代码会很长。用函数封装起来，代码就简洁多了！\"\n\n**禁忌提醒**\n❌ 函数名用中文——会报错\n❌ 忘记调用函数——定义了但没执行\n\n---\n\n**核心知识点**\n- 函数定义：`def` 关键字\n- 函数调用：将重复的攻击或移动逻辑封装成\"积木\"\n- 代码复用：使代码更简洁、可复用\n\n**教学类比**\n> 函数就像\"打包\"代码的工具，把重复的动作装进一个盒子里，需要时拿出来用。\n\n`#执行层` `#测评项`\n[UID: PYAI-11-01-001]\n\n---\n\n### 1-1-2 未雨绸缪\n\n#### 课程基本信息\n\n| 项目 | 内容 |\n|------|------|\n| **课程编号** | 1-1-2 |\n| **课程名称** | 未雨绸缪 |\n| **认知负荷** | 高 |\n| **核心技能** | 形式参数、实际参数 |\n\n#### 详细教学流程\n\n**步骤1：知识讲解（15分钟）** `#中负荷-操练` `#IFC-即时`\n\n**教师话术**\n> \"上节课的函数只能做固定的事。如果我想让函数更灵活，能根据不同情况做不同的事，怎么办？——用**参数**！\"\n>\n> \"**形式参数(Parameter)**：函数定义时的'占位符'\n> **实际参数(Argument)**：调用时传递的'具体值'\n>\n> ```python\n> def attack_target(target):  # target是形参\n>     hero.attack(target)\n>\n> enemy = hero.findNearestEnemy()\n> attack_target(enemy)  # enemy是实参\n> ```\"\n\n**变体示例**\n\n| 学生情况 | 调整方案 | 说明 |\n|----------|----------|------|\n| 混淆形参实参 | 自动贩卖机类比 | \"形参是投币口，实参是你投的硬币\" |\n| 参数数量不对 | 强调匹配 | 定义几个形参，调用就要传几个实参 |\n| 想传多个参数 | 预告下节课 | 下节课学习多参数函数 |\n\n---\n\n**核心知识点**\n- 形式参数(Parameter)：函数定义时的\"占位符\"\n- 实际参数(Argument)：调用时传递的\"具体值\"\n- 参数类型：调用时必须传递具体数值或字符串\n\n**教学类比**\n> 形参与实参就像\"自动贩卖机（函数）- 投币（参数）- 出货（返回值）\"\n\n`#执行层` `#测评项`\n[UID: PYAI-11-02-001]\n\n---\n\n### 1-1-3 棱角分明\n\n#### 课程基本信息\n\n| 项目 | 内容 |\n|------|------|\n| **课程编号** | 1-1-3 |\n| **课程名称** | 棱角分明 |\n| **认知负荷** | 中-高 |\n| **核心技能** | 绘图指令、参数应用、几何逻辑 |\n\n#### 详细教学流程\n\n**步骤1：知识讲解（15分钟）** `#中负荷-操练` `#IFC-即时`\n\n**教师话术**\n> \"今天我们用函数来画图！还记得上节课学的参数吗？现在我们用参数来控制画多边形。\"\n>\n> \"画正方形需要4条边，每条边转90度。画三角形需要3条边，每条边转120度。发现规律了吗？\n> ```python\n> def draw_polygon(sides, length):\n>     angle = 360 / sides  # 计算转角\n>     for i in range(sides):\n>         hero.moveXY(length, 0)\n>         hero.turn(angle)\n> ```\n>\n> 调用时传入边数和边长：\n> ```python\n> draw_polygon(4, 50)   # 画正方形\n> draw_polygon(6, 30)   # 画六边形\n> ```\"\n\n**变体示例**\n\n| 学生情况 | 调整方案 | 说明 |\n|----------|----------|------|\n| 不理解角度计算 | 用披萨类比 | \"360度的披萨切成n份，每份就是360/n度\" |\n| 画出来形状不对 | 检查循环次数 | 边数和循环次数要一致 |\n| 想画更复杂图形 | 鼓励尝试 | 可以画星形、螺旋等 |\n\n---\n\n**步骤2：闯关实践（35分钟）** `#高负荷-产出` `#IFC-即时`\n\n**教师话术**\n> \"现在进入绘图挑战！用你的函数画出三角形、正方形、五边形、六边形。看谁画得又快又准！\"\n\n**禁忌提醒**\n❌ 角度计算错误——图形无法闭合\n❌ 忘记循环——只画一条边\n\n---\n\n**核心知识点**\n- 绘图指令：移动和转向的组合\n- 参数应用：用参数控制边数和边长\n- 几何逻辑：外角和 = 360度\n\n**教学类比**\n> 画多边形就像走迷宫，每走一步转一个角度，走完一圈回到原点。\n\n`#执行层` `#测评项`\n[UID: PYAI-11-03-001]\n\n---\n\n### 1-1-4 对照实验\n\n#### 课程基本信息\n\n| 项目 | 内容 |\n|------|------|\n| **课程编号** | 1-1-4 |\n| **课程名称** | 对照实验 |\n| **认知负荷** | 高 |\n| **核心技能** | 多参数函数、位置参数 |\n\n#### 详细教学流程\n\n**步骤1：知识讲解（15分钟）** `#中负荷-操练` `#IFC-即时`\n\n**教师话术**\n> \"之前我们的函数只有一两个参数，今天来学习**多参数函数**！参数可以有很多个，用逗号隔开。\"\n>\n> \"**位置参数**：按顺序传递，位置很重要！\n> ```python\n> def move_and_attack(x, y, target):\n>     hero.moveXY(x, y)\n>     hero.attack(target)\n>\n> # 调用时参数顺序要对应\n> move_and_attack(30, 40, enemy)  # x=30, y=40, target=enemy\n> ```\n>\n> 如果顺序搞错了，程序就会出问题！\"\n\n**变体示例**\n\n| 学生情况 | 调整方案 | 说明 |\n|----------|----------|------|\n| 参数顺序搞混 | 用点餐类比 | \"就像点餐：主食、饮料、甜点，顺序不能乱\" |\n| 参数太多记不住 | 建议命名 | 函数名和参数名要见名知意 |\n| 想用关键字参数 | 预告后续 | 可以用name=value的方式调用 |\n\n---\n\n**步骤2：闯关实践（35分钟）** `#高负荷-产出` `#IFC-即时`\n\n**教师话术**\n> \"返回荆棘农场！这次敌人分布在不同位置，你需要写一个函数，传入坐标和目标，让英雄移动到指定位置并攻击。参数顺序一定要对！\"\n\n**禁忌提醒**\n❌ 参数顺序错误——移动到错误位置\n❌ 参数数量不匹配——TypeError错误\n\n---\n\n**核心知识点**\n- 多参数函数：用逗号分隔多个参数\n- 位置参数：按定义顺序传递\n- 参数匹配：实参数量和类型要与形参对应\n\n**教学类比**\n> 多参数就像填表格，每个空格都要填对应的内容，顺序不能乱。\n\n`#执行层` `#测评项`\n[UID: PYAI-11-04-001]\n\n---\n\n### 1-1-5 电光火石\n\n#### 课程基本信息\n\n| 项目 | 内容 |\n|------|------|\n| **课程编号** | 1-1-5 |\n| **课程名称** | 电光火石 |\n| **认知负荷** | 高 |\n| **核心技能** | 默认参数、变量作用域 |\n\n#### 详细教学流程\n\n**步骤1：知识讲解（15分钟）** `#中负荷-操练` `#IFC-即时`\n\n**教师话术**\n> \"如果调用函数时不想每次都传参数，可以设置**默认参数**：\n> ```python\n> def greet(name='Friend'):\n>     print(f'Hello, {name}!')\n>\n> greet()        # 输出: Hello, Friend!\n> greet('Tom')   # 输出: Hello, Tom!\n> ```\n>\n> 还有一个重要概念：**作用域**。函数内的变量（局部变量）和外部变量（全局变量）是不一样的！\"\n\n**变体示例**\n\n| 学生情况 | 调整方案 | 说明 |\n|----------|----------|------|\n| 不理解作用域 | 用房间类比 | \"局部变量只在函数这个'房间'里有效\" |\n| 默认参数写错位置 | 强调顺序 | 默认参数必须放在非默认参数后面 |\n| 想修改全局变量 | 介绍global | 用global关键字声明 |\n\n---\n\n**核心知识点**\n- 默认参数：`def greet(name=\"Friend\")`\n- 局部变量vs全局变量：函数内的变量（局部）与外部变量的区别\n\n`#执行层` `#测评项`\n[UID: PYAI-11-05-001]\n\n---\n\n### 1-1-6 言听计从1\n\n#### 课程基本信息\n\n| 项目 | 内容 |\n|------|------|\n| **课程编号** | 1-1-6 |\n| **课程名称** | 言听计从1 |\n| **认知负荷** | 高 |\n| **核心技能** | 事件监听、pet.on()、hear/spawn事件 |\n\n#### 详细教学流程\n\n**步骤1：知识讲解（15分钟）** `#中负荷-操练` `#IFC-即时`\n\n**教师话术**\n> \"今天我们学习一个神奇的概念——**事件监听**！之前我们的程序是'顺序执行'，今天要转向'事件驱动'思维。\"\n>\n> \"**事件监听**就是让程序'等待'某件事发生，然后自动执行对应的函数：\n> ```python\n> def speak(event):\n>     pet.say('喵~')\n>\n> pet.on('hear', speak)  # 当听到声音时，执行speak函数\n> hero.say('你好小猫')    # 触发hear事件\n> ```\n>\n> **事件类型**：\n> - `'hear'`：听到说话时触发\n> - `'spawn'`：物体/单位生成时触发\"\n\n**变体示例**\n\n| 学生情况 | 调整方案 | 说明 |\n|----------|----------|------|\n| 不理解事件驱动 | 用门铃类比 | \"就像门铃，有人按了才响，不是一直响\" |\n| 忘记绑定事件 | 强调pet.on() | \"必须先用on()绑定，事件才会触发函数\" |\n| 想监听更多事件 | 介绍spawn | \"spawn事件在物品生成时触发\" |\n\n---\n\n**步骤2：闯关实践（35分钟）** `#高负荷-产出` `#IFC-即时`\n\n**教师话术**\n> \"进入关卡'边地好伙伴'！让你的宠物听到暗号后回应。然后挑战'森林加农炮'，结合循环与事件的复杂应用！\"\n\n**核心代码模式**\n\n```python\n# 示例1：听到声音后回答（Hear Event）\ndef speak(event):\n    pet.say(\"喵~\")\n\npet.on(\"hear\", speak)\nhero.say(\"你好小猫\")\n\n# 示例2：物品生成后去捡（Spawn Event）\ndef goFetch():\n    potion = hero.findNearestItem()\n    if potion:\n        pet.fetch(potion)\n\npet.on(\"spawn\", goFetch)\n```\n\n**禁忌提醒**\n❌ 忘记绑定事件——函数定义了但不会被触发\n❌ 事件类型拼写错误——'hear'不是'here'\n\n---\n\n**核心知识点**\n- 事件监听：`pet.on(\"event_type\", function_name)`\n- 事件处理函数：当事件发生时自动调用的函数\n- 事件类型：hear（听到说话）、spawn（物体生成）\n\n**教学类比**\n> 事件监听就像设置闹钟，闹钟响了（事件发生）才会叫你起床（执行函数）。\n\n`#执行层` `#测评项`\n[UID: PYAI-11-06-001]\n\n---\n\n### 1-1-7 棋逢对手\n\n#### 课程基本信息\n\n| 项目 | 内容 |\n|------|------|\n| **课程编号** | 1-1-7 |\n| **课程名称** | 棋逢对手 |\n| **认知负荷** | 高 |\n| **核心技能** | 策略制定、红蓝对抗 |\n\n#### 详细教学流程\n\n**步骤1：知识讲解（15分钟）** `#中负荷-操练` `#IFC-即时`\n\n**教师话术**\n> \"今天是激动人心的**竞技场对战**！你要用学过的所有函数知识，编写一个AI来和对手PK！\"\n>\n> \"策略制定的关键：\n> ```python\n> def choose_action():\n>     enemy = hero.findNearestEnemy()\n>     if hero.health < 50:\n>         return 'retreat'  # 血量低就撤退\n>     elif enemy and hero.distanceTo(enemy) < 10:\n>         return 'attack'   # 敌人近就攻击\n>     else:\n>         return 'advance'  # 否则前进\n> ```\n>\n> 好的策略要考虑：血量、距离、敌人数量等多种因素！\"\n\n**变体示例**\n\n| 学生情况 | 调整方案 | 说明 |\n|----------|----------|------|\n| 策略太简单 | 引导思考 | \"如果敌人很多怎么办？如果有队友呢？\" |\n| 代码太乱 | 模块化建议 | 把攻击、防御、移动分成不同函数 |\n| 想看别人策略 | 组织分享 | 让同学互相展示和学习 |\n\n---\n\n**步骤2：竞技实践（35分钟）** `#高负荷-产出` `#IFC-即时`\n\n**教师话术**\n> \"现在进入红蓝对抗！你的代码就是你的军师，帮你的英雄做出最佳决策。看谁的策略更厉害！\"\n\n**禁忌提醒**\n❌ 只攻不守——容易被反杀\n❌ 策略单一——容易被针对\n\n---\n\n**核心知识点**\n- 策略制定：根据条件选择不同行动\n- 函数综合：组合多个函数实现复杂逻辑\n- 红蓝对抗：实时对战检验代码质量\n\n**教学类比**\n> 编写AI策略就像当军师，要根据战场形势随机应变。\n\n`#执行层` `#测评项`\n[UID: PYAI-11-07-001]\n\n---\n\n### 1-1-8 量入为出\n\n#### 课程基本信息\n\n| 项目 | 内容 |\n|------|------|\n| **课程编号** | 1-1-8 |\n| **课程名称** | 量入为出 |\n| **认知负荷** | 中-高 |\n| **核心技能** | input输入、类型转换、f-string格式化 |\n\n#### 详细教学流程\n\n**步骤1：知识讲解（15分钟）** `#中负荷-操练` `#IFC-即时`\n\n**教师话术**\n> \"之前我们的程序都是'自说自话'，今天学习**人机交互**——让程序和用户对话！\"\n>\n> \"**input()函数**：获取用户输入\n> ```python\n> name = input('请输入你的名字：')\n> print(f'你好，{name}！')\n> ```\n>\n> 注意：input()返回的是**字符串**！如果要做数学运算，需要**类型转换**：\n> ```python\n> age = input('请输入你的年龄：')\n> age = int(age)  # 转换为整数\n> print(f'明年你就{age + 1}岁了！')\n> ```\"\n\n**变体示例**\n\n| 学生情况 | 调整方案 | 说明 |\n|----------|----------|------|\n| 忘记类型转换 | 演示错误 | 字符串'5' + 1会报错 |\n| f-string语法错误 | 强调格式 | f开头，变量用{}包裹 |\n| 想做更多交互 | 鼓励创意 | 可以做问答游戏、调查问卷 |\n\n---\n\n**步骤2：项目实践（35分钟）** `#高负荷-产出` `#IFC-即时`\n\n**教师话术**\n> \"现在来做一个**交互式自我介绍程序**！让程序问用户的名字、年龄、爱好，然后生成一段个性化的介绍。\"\n\n**禁忌提醒**\n❌ 忘记类型转换——数字运算出错\n❌ f-string忘记f——变量不会被替换\n\n---\n\n**核心知识点**\n- input()函数：获取用户键盘输入\n- 类型转换：int()、float()、str()\n- f-string格式化：f'文本{变量}'\n\n**教学类比**\n> input就像程序的\"耳朵\"，能听到用户说什么；print就像\"嘴巴\"，能回应用户。\n\n`#执行层` `#测评项`\n[UID: PYAI-11-08-001]\n\n---\n\n### 1-1-9 算术运算\n\n#### 课程基本信息\n\n| 项目 | 内容 |\n|------|------|\n| **课程编号** | 1-1-9 |\n| **课程名称** | 算术运算 |\n| **认知负荷** | 高 |\n| **核心技能** | 算术运算符、eval()函数 |\n\n#### 详细教学流程\n\n**步骤1：知识讲解（15分钟）** `#中负荷-操练` `#IFC-即时`\n\n**教师话术**\n> \"今天学习Python的**算术运算符**，有些你可能没见过！\"\n>\n> \"常见运算符：\n> - `+` `-` `*` `/`：加减乘除\n> - `//`：**整除**（只取整数部分）\n> - `%`：**取余**（除法的余数）\n> - `**`：**幂运算**（乘方）\n>\n> ```python\n> print(7 // 2)   # 输出: 3（整除）\n> print(7 % 2)    # 输出: 1（余数）\n> print(2 ** 3)   # 输出: 8（2的3次方）\n> ```\n>\n> 还有一个神奇的**eval()函数**，可以把字符串当代码执行：\n> ```python\n> result = eval('2 + 3 * 4')\n> print(result)  # 输出: 14\n> ```\"\n\n**变体示例**\n\n| 学生情况 | 调整方案 | 说明 |\n|----------|----------|------|\n| 混淆/和// | 对比演示 | 7/2=3.5，7//2=3 |\n| 不理解取余 | 用分糖果类比 | \"7颗糖分给2人，每人3颗，剩1颗\" |\n| 对eval好奇 | 安全提醒 | eval很强大但要小心，不要执行不信任的输入 |\n\n---\n\n**步骤2：项目实践（35分钟）** `#高负荷-产出` `#IFC-即时`\n\n**教师话术**\n> \"现在来做一个**简易计算器**！用户输入算式，程序输出结果。可以用eval()来实现，也可以自己解析算式。\"\n\n**禁忌提醒**\n❌ 除以0——ZeroDivisionError\n❌ eval执行危险代码——安全隐患\n\n---\n\n**核心知识点**\n- 整除运算符：`//`\n- 取余运算符：`%`\n- 幂运算符：`**`\n- eval()函数：执行字符串表达式\n\n**教学类比**\n> 整除就像分东西只要整数，取余就是分完剩下的。\n\n`#执行层` `#测评项`\n[UID: PYAI-11-09-001]\n\n---\n\n### 1-1-10 关系运算\n\n#### 课程基本信息\n\n| 项目 | 内容 |\n|------|------|\n| **课程编号** | 1-1-10 |\n| **课程名称** | 关系运算 |\n| **认知负荷** | 中-高 |\n| **核心技能** | 比较运算符、布尔值、变量交换 |\n\n#### 详细教学流程\n\n**步骤1：知识讲解（15分钟）** `#中负荷-操练` `#IFC-即时`\n\n**教师话术**\n> \"今天学习**关系运算符**，也叫比较运算符。它们的结果是**布尔值**：True或False。\"\n>\n> \"比较运算符：\n> - `==`：等于（注意是两个等号！）\n> - `!=`：不等于\n> - `>`、`<`：大于、小于\n> - `>=`、`<=`：大于等于、小于等于\n>\n> ```python\n> print(5 == 5)   # True\n> print(5 != 3)   # True\n> print(5 > 10)   # False\n> ```\n>\n> 还有一个经典问题：**如何交换两个变量的值？**\n> ```python\n> a, b = 10, 20\n> a, b = b, a  # Python的优雅写法\n> print(a, b)  # 输出: 20 10\n> ```\"\n\n**变体示例**\n\n| 学生情况 | 调整方案 | 说明 |\n|----------|----------|------|\n| 混淆=和== | 反复强调 | \"一个等号是赋值，两个等号是比较\" |\n| 不理解布尔值 | 用判断题类比 | \"就像判断题，对就是True，错就是False\" |\n| 变量交换不理解 | 用杯子类比 | 传统方法需要第三个杯子，Python可以直接交换 |\n\n---\n\n**步骤2：项目实践（35分钟）** `#高负荷-产出` `#IFC-即时`\n\n**教师话术**\n> \"现在来做一个**数字比较游戏**！程序生成两个随机数，用户判断它们的大小关系，程序验证答案是否正确。\"\n\n**禁忌提醒**\n❌ 用=做比较——变成赋值语句\n❌ 比较不同类型——可能得到意外结果\n\n---\n\n**核心知识点**\n- 比较运算符：==、!=、>、<、>=、<=\n- 布尔值：True和False\n- 变量交换：a, b = b, a\n\n**教学类比**\n> 比较运算就像裁判，判断两边谁大谁小，给出True或False的判决。\n\n`#执行层` `#测评项`\n[UID: PYAI-11-10-001]\n\n---\n\n### 1-1-11 碰撞检测\n\n#### 课程基本信息\n\n| 项目 | 内容 |\n|------|------|\n| **课程编号** | 1-1-11 |\n| **课程名称** | 碰撞检测 |\n| **认知负荷** | 高 |\n| **核心技能** | 碰撞原理、distanceTo、touching |\n\n#### 详细教学流程\n\n**步骤1：知识讲解（15分钟）** `#中负荷-操练` `#IFC-即时`\n\n**教师话术**\n> \"今天是本单元的最后一课，我们来学习游戏开发中超级重要的概念——**碰撞检测**！\"\n>\n> \"碰撞检测的原理：判断两个物体是否接触。\n>\n> **方法1：距离判断**\n> ```python\n> distance = hero.distanceTo(enemy)\n> if distance < 5:\n>     print('碰撞了！')\n> ```\n>\n> **方法2：touching方法**\n> ```python\n> if hero.touching(enemy):\n>     print('碰撞了！')\n> ```\n>\n> 碰撞检测在游戏中无处不在：吃金币、撞敌人、踩平台...\"\n\n**变体示例**\n\n| 学生情况 | 调整方案 | 说明 |\n|----------|----------|------|\n| 不理解距离判断 | 画图演示 | 两个圆心距离小于半径之和就碰撞 |\n| 碰撞检测不灵敏 | 调整阈值 | 距离阈值可能需要根据物体大小调整 |\n| 想做更复杂碰撞 | 介绍概念 | 矩形碰撞、像素碰撞等高级方法 |\n\n---\n\n**步骤2：项目实践（35分钟）** `#高负荷-产出` `#IFC-即时`\n\n**教师话术**\n> \"现在来做两个小项目：\n> 1. **月食模拟**：当月亮和太阳重叠时，显示'月食发生！'\n> 2. **交通避让**：控制小车躲避障碍物，碰到就游戏结束。\n>\n> 这是本单元的综合应用，用上你学过的所有知识！\"\n\n**禁忌提醒**\n❌ 碰撞阈值设太小——检测不到碰撞\n❌ 忘记持续检测——只检测一次\n\n---\n\n**核心知识点**\n- 碰撞原理：判断两物体是否接触\n- distanceTo()：计算两点距离\n- touching()：直接判断是否接触\n- 综合应用：结合函数、条件、循环\n\n**教学类比**\n> 碰撞检测就像游戏里的\"触觉\"，让程序知道物体之间有没有接触。\n\n`#执行层` `#测评项`\n[UID: PYAI-11-11-001]\n\n---"
    },
    {
      "title": "教学禁忌清单",
      "content": "| 序号 | 禁忌 | 原因 | 正确做法 |\n|------|------|------|----------|\n| 1 | 账号安全违规 | 影响教学活动 | 不将公用账号交给学生，不私自修改密码 |\n| 2 | 参数列表不匹配 | TypeError错误 | 实参数量必须与形参匹配（除非有默认值） |\n| 3 | 混淆`=`和`==` | 逻辑错误 | 赋值用`=`，比较用`==` |\n| 4 | 函数名不规范 | 可读性差 | 用小写字母和下划线，如attack_enemy |\n| 5 | 忘记调用函数 | 定义了但没执行 | 定义后必须调用 |\n\n`#执行层` `#测评项`\n[UID: PYAI-TABOO-11]\n\n---"
    },
    {
      "title": "教学注意事项",
      "content": "| 类别 | 注意事项 |\n|------|----------|\n| **形参与实参** | 反复强调形参是\"占位符\"，实参是\"具体值\" |\n| **作用域** | 函数内部定义的变量（局部）在外部无法访问 |\n| **调试技巧** | 使用print()输出变量值或函数返回值 |\n| **命名规范** | 函数名用小写字母和下划线，见名知意 |\n\n---"
    },
    {
      "title": "底层教育学原理",
      "content": "| 原理 | 说明 | 在本单元的应用 |\n|------|------|----------------|\n| **模块化思维** | 将复杂问题拆分为可复用模块 | 函数封装重复代码 |\n| **抽象思维** | 用参数实现泛化 | 同一函数处理不同数据 |\n| **螺旋式上升** | 知识点逐步加深 | 无参数→有参数→默认参数→多参数 |\n\n`#执行层` `#测评项`\n[UID: PYAI-THEORY-11]\n\n---\n\n**质量评估**：10/10（原子化萃取版）\n**已补充**：认知负荷标签、IFC标签、变体示例、详细教师话术\n\n---\n\n**最后更新**：2026-02-09"
    }
  ],
  "full_content": "# PythonAI萃取：L1-1 函数封装与交互\n\n> **来源**：NotebookLM Python AI Lesson Plan (96个来源)\n> **萃取日期**：2026-02-02\n> **萃取深度**：5-5多维度（含认知负荷标签、IFC标签、变体示例）\n> **更新日期**：2026-02-04\n\n---\n\n## 单元概览\n\n| 项目 | 内容 |\n|------|------|\n| **单元编号** | PYAI 1-1 |\n| **单元名称** | 函数封装与交互机制 |\n| **适用年龄** | 三年级及以上（8-10岁） |\n| **课时数** | 11节 × 90分钟 |\n| **核心目标** | 从顺序执行转向模块化编程，掌握函数定义与调用 |\n| **主要平台** | CodeCombat |\n\n**底层逻辑**\n掌握函数的定义与调用，并引入人机交互（输入/输出/事件），培养模块化编程思想。\n\n**单元教学策略**\n- 函数基础（01-04）：def定义、参数、多参数\n- 高级概念（05-07）：默认参数、作用域、策略\n- 交互应用（08-11）：input、运算、碰撞检测\n\n`#执行层` `#测评项`\n[UID: PYAI-11-001]\n[关联: PYAI-10-001 PythonAI基础语法（前置基础）]\n[关联: PYAI-12-001 PythonAI算法逻辑（进阶衔接）]\n\n---\n\n## 课程列表\n\n| 课次 | 课程名称 | 核心知识点 | 项目/关卡 | 认知负荷 |\n|------|----------|------------|-----------|----------|\n| 1-1-1 | 一夫当关 | 函数定义(def)、函数调用、代码复用 | 乡村巡游者 | 中-高 |\n| 1-1-2 | 未雨绸缪 | 形式参数、实际参数、参数类型 | 迷藏 | 高 |\n| 1-1-3 | 棱角分明 | 绘图指令、参数应用、几何逻辑 | 绘制多边形 | 中-高 |\n| 1-1-4 | 对照实验 | 多参数函数、位置参数 | 返回荆棘农场 | 高 |\n| 1-1-5 | 电光火石 | 默认参数、局部变量vs全局变量 | 函数巡逻 | 高 |\n| 1-1-6 | 言听计从1 | 事件监听、pet.on()、hear/spawn事件 | 边地好伙伴 | 高 |\n| 1-1-7 | 棋逢对手 | 策略制定、红蓝对抗 | 竞技场 | 高 |\n| 1-1-8 | 量入为出 | input输入、类型转换、f-string格式化 | 交互式对话 | 中-高 |\n| 1-1-9 | 算术运算 | 算术运算符(//, %, **)、eval()函数 | 简易计算器 | 高 |\n| 1-1-10 | 关系运算 | 比较运算符、布尔值、变量交换 | 变量交换 | 中-高 |\n| 1-1-11 | 碰撞检测 | 碰撞原理、distanceTo、touching | 月食/交通 | 高 |\n\n---\n\n## 通用教学流程（90分钟）\n\n| 环节 | 时间 | 内容 | 认知负荷 | IFC标签 |\n|------|------|------|----------|---------|\n| 课堂问候 | 2分钟 | 自我介绍、学习目标 | `#低负荷-热身` | `#IFC-预防` |\n| 课程回顾 | 5分钟 | 复习上节课代码知识 | `#低负荷-热身` | `#IFC-预防` |\n| 知识讲解 | 15分钟 | 新语法/概念讲解 | `#中负荷-操练` | `#IFC-即时` |\n| 闯关实践 | 35分钟 | CodeCombat闯关 | `#高负荷-产出` | `#IFC-即时` |\n| 调节休息 | 3分钟 | 站起来活动、眼保健操 | `#调节-放松` | - |\n| 项目创作 | 20分钟 | 综合项目/自由创作 | `#高负荷-产出` | `#IFC-即时` |\n| 成果展示 | 10分钟 | 分享代码、讲解思路 | `#低负荷-热身` | `#IFC-复盘` |\n\n`#执行层` `#测评项`\n[UID: PYAI-11-FLOW-001]\n\n---\n\n## 详细课程萃取\n\n### 1-1-1 一夫当关（典型案例）\n\n#### 课程基本信息\n\n| 项目 | 内容 |\n|------|------|\n| **课程编号** | 1-1-1 |\n| **课程名称** | 一夫当关 |\n| **认知负荷** | 中-高 |\n| **核心技能** | 函数定义、函数调用、代码复用 |\n\n#### 详细教学流程\n\n**步骤1：知识讲解（15分钟）** `#中负荷-操练` `#IFC-即时`\n\n**教师话术**\n> \"今天我们学习一个超级重要的概念——**函数**！函数就像'打包'代码的工具，把重复的动作装进一个盒子里，需要时拿出来用。\"\n>\n> \"定义函数用 `def` 关键字：\n> ```python\n> def attack_enemy():\n>     enemy = hero.findNearestEnemy()\n>     if enemy:\n>         hero.attack(enemy)\n> ```\n>\n> 调用函数就是喊一声它的名字：\n> ```python\n> attack_enemy()  # 执行攻击函数\n> ```\"\n\n**变体示例**\n\n| 学生情况 | 调整方案 | 说明 |\n|----------|----------|------|\n| 不理解函数用途 | 用遥控器类比 | \"函数就像遥控器按钮，按一下执行一串动作\" |\n| 忘记冒号 | 口诀强化 | \"def后面要冒号，缩进代码不能少\" |\n| 想了解更多 | 介绍内置函数 | print()、len()都是函数 |\n\n---\n\n**步骤2：闯关实践（35分钟）** `#高负荷-产出` `#IFC-即时`\n\n**教师话术**\n> \"现在进入CodeCombat闯关！这一关敌人很多，如果每次都写攻击代码会很长。用函数封装起来，代码就简洁多了！\"\n\n**禁忌提醒**\n❌ 函数名用中文——会报错\n❌ 忘记调用函数——定义了但没执行\n\n---\n\n**核心知识点**\n- 函数定义：`def` 关键字\n- 函数调用：将重复的攻击或移动逻辑封装成\"积木\"\n- 代码复用：使代码更简洁、可复用\n\n**教学类比**\n> 函数就像\"打包\"代码的工具，把重复的动作装进一个盒子里，需要时拿出来用。\n\n`#执行层` `#测评项`\n[UID: PYAI-11-01-001]\n\n---\n\n### 1-1-2 未雨绸缪\n\n#### 课程基本信息\n\n| 项目 | 内容 |\n|------|------|\n| **课程编号** | 1-1-2 |\n| **课程名称** | 未雨绸缪 |\n| **认知负荷** | 高 |\n| **核心技能** | 形式参数、实际参数 |\n\n#### 详细教学流程\n\n**步骤1：知识讲解（15分钟）** `#中负荷-操练` `#IFC-即时`\n\n**教师话术**\n> \"上节课的函数只能做固定的事。如果我想让函数更灵活，能根据不同情况做不同的事，怎么办？——用**参数**！\"\n>\n> \"**形式参数(Parameter)**：函数定义时的'占位符'\n> **实际参数(Argument)**：调用时传递的'具体值'\n>\n> ```python\n> def attack_target(target):  # target是形参\n>     hero.attack(target)\n>\n> enemy = hero.findNearestEnemy()\n> attack_target(enemy)  # enemy是实参\n> ```\"\n\n**变体示例**\n\n| 学生情况 | 调整方案 | 说明 |\n|----------|----------|------|\n| 混淆形参实参 | 自动贩卖机类比 | \"形参是投币口，实参是你投的硬币\" |\n| 参数数量不对 | 强调匹配 | 定义几个形参，调用就要传几个实参 |\n| 想传多个参数 | 预告下节课 | 下节课学习多参数函数 |\n\n---\n\n**核心知识点**\n- 形式参数(Parameter)：函数定义时的\"占位符\"\n- 实际参数(Argument)：调用时传递的\"具体值\"\n- 参数类型：调用时必须传递具体数值或字符串\n\n**教学类比**\n> 形参与实参就像\"自动贩卖机（函数）- 投币（参数）- 出货（返回值）\"\n\n`#执行层` `#测评项`\n[UID: PYAI-11-02-001]\n\n---\n\n### 1-1-3 棱角分明\n\n#### 课程基本信息\n\n| 项目 | 内容 |\n|------|------|\n| **课程编号** | 1-1-3 |\n| **课程名称** | 棱角分明 |\n| **认知负荷** | 中-高 |\n| **核心技能** | 绘图指令、参数应用、几何逻辑 |\n\n#### 详细教学流程\n\n**步骤1：知识讲解（15分钟）** `#中负荷-操练` `#IFC-即时`\n\n**教师话术**\n> \"今天我们用函数来画图！还记得上节课学的参数吗？现在我们用参数来控制画多边形。\"\n>\n> \"画正方形需要4条边，每条边转90度。画三角形需要3条边，每条边转120度。发现规律了吗？\n> ```python\n> def draw_polygon(sides, length):\n>     angle = 360 / sides  # 计算转角\n>     for i in range(sides):\n>         hero.moveXY(length, 0)\n>         hero.turn(angle)\n> ```\n>\n> 调用时传入边数和边长：\n> ```python\n> draw_polygon(4, 50)   # 画正方形\n> draw_polygon(6, 30)   # 画六边形\n> ```\"\n\n**变体示例**\n\n| 学生情况 | 调整方案 | 说明 |\n|----------|----------|------|\n| 不理解角度计算 | 用披萨类比 | \"360度的披萨切成n份，每份就是360/n度\" |\n| 画出来形状不对 | 检查循环次数 | 边数和循环次数要一致 |\n| 想画更复杂图形 | 鼓励尝试 | 可以画星形、螺旋等 |\n\n---\n\n**步骤2：闯关实践（35分钟）** `#高负荷-产出` `#IFC-即时`\n\n**教师话术**\n> \"现在进入绘图挑战！用你的函数画出三角形、正方形、五边形、六边形。看谁画得又快又准！\"\n\n**禁忌提醒**\n❌ 角度计算错误——图形无法闭合\n❌ 忘记循环——只画一条边\n\n---\n\n**核心知识点**\n- 绘图指令：移动和转向的组合\n- 参数应用：用参数控制边数和边长\n- 几何逻辑：外角和 = 360度\n\n**教学类比**\n> 画多边形就像走迷宫，每走一步转一个角度，走完一圈回到原点。\n\n`#执行层` `#测评项`\n[UID: PYAI-11-03-001]\n\n---\n\n### 1-1-4 对照实验\n\n#### 课程基本信息\n\n| 项目 | 内容 |\n|------|------|\n| **课程编号** | 1-1-4 |\n| **课程名称** | 对照实验 |\n| **认知负荷** | 高 |\n| **核心技能** | 多参数函数、位置参数 |\n\n#### 详细教学流程\n\n**步骤1：知识讲解（15分钟）** `#中负荷-操练` `#IFC-即时`\n\n**教师话术**\n> \"之前我们的函数只有一两个参数，今天来学习**多参数函数**！参数可以有很多个，用逗号隔开。\"\n>\n> \"**位置参数**：按顺序传递，位置很重要！\n> ```python\n> def move_and_attack(x, y, target):\n>     hero.moveXY(x, y)\n>     hero.attack(target)\n>\n> # 调用时参数顺序要对应\n> move_and_attack(30, 40, enemy)  # x=30, y=40, target=enemy\n> ```\n>\n> 如果顺序搞错了，程序就会出问题！\"\n\n**变体示例**\n\n| 学生情况 | 调整方案 | 说明 |\n|----------|----------|------|\n| 参数顺序搞混 | 用点餐类比 | \"就像点餐：主食、饮料、甜点，顺序不能乱\" |\n| 参数太多记不住 | 建议命名 | 函数名和参数名要见名知意 |\n| 想用关键字参数 | 预告后续 | 可以用name=value的方式调用 |\n\n---\n\n**步骤2：闯关实践（35分钟）** `#高负荷-产出` `#IFC-即时`\n\n**教师话术**\n> \"返回荆棘农场！这次敌人分布在不同位置，你需要写一个函数，传入坐标和目标，让英雄移动到指定位置并攻击。参数顺序一定要对！\"\n\n**禁忌提醒**\n❌ 参数顺序错误——移动到错误位置\n❌ 参数数量不匹配——TypeError错误\n\n---\n\n**核心知识点**\n- 多参数函数：用逗号分隔多个参数\n- 位置参数：按定义顺序传递\n- 参数匹配：实参数量和类型要与形参对应\n\n**教学类比**\n> 多参数就像填表格，每个空格都要填对应的内容，顺序不能乱。\n\n`#执行层` `#测评项`\n[UID: PYAI-11-04-001]\n\n---\n\n### 1-1-5 电光火石\n\n#### 课程基本信息\n\n| 项目 | 内容 |\n|------|------|\n| **课程编号** | 1-1-5 |\n| **课程名称** | 电光火石 |\n| **认知负荷** | 高 |\n| **核心技能** | 默认参数、变量作用域 |\n\n#### 详细教学流程\n\n**步骤1：知识讲解（15分钟）** `#中负荷-操练` `#IFC-即时`\n\n**教师话术**\n> \"如果调用函数时不想每次都传参数，可以设置**默认参数**：\n> ```python\n> def greet(name='Friend'):\n>     print(f'Hello, {name}!')\n>\n> greet()        # 输出: Hello, Friend!\n> greet('Tom')   # 输出: Hello, Tom!\n> ```\n>\n> 还有一个重要概念：**作用域**。函数内的变量（局部变量）和外部变量（全局变量）是不一样的！\"\n\n**变体示例**\n\n| 学生情况 | 调整方案 | 说明 |\n|----------|----------|------|\n| 不理解作用域 | 用房间类比 | \"局部变量只在函数这个'房间'里有效\" |\n| 默认参数写错位置 | 强调顺序 | 默认参数必须放在非默认参数后面 |\n| 想修改全局变量 | 介绍global | 用global关键字声明 |\n\n---\n\n**核心知识点**\n- 默认参数：`def greet(name=\"Friend\")`\n- 局部变量vs全局变量：函数内的变量（局部）与外部变量的区别\n\n`#执行层` `#测评项`\n[UID: PYAI-11-05-001]\n\n---\n\n### 1-1-6 言听计从1\n\n#### 课程基本信息\n\n| 项目 | 内容 |\n|------|------|\n| **课程编号** | 1-1-6 |\n| **课程名称** | 言听计从1 |\n| **认知负荷** | 高 |\n| **核心技能** | 事件监听、pet.on()、hear/spawn事件 |\n\n#### 详细教学流程\n\n**步骤1：知识讲解（15分钟）** `#中负荷-操练` `#IFC-即时`\n\n**教师话术**\n> \"今天我们学习一个神奇的概念——**事件监听**！之前我们的程序是'顺序执行'，今天要转向'事件驱动'思维。\"\n>\n> \"**事件监听**就是让程序'等待'某件事发生，然后自动执行对应的函数：\n> ```python\n> def speak(event):\n>     pet.say('喵~')\n>\n> pet.on('hear', speak)  # 当听到声音时，执行speak函数\n> hero.say('你好小猫')    # 触发hear事件\n> ```\n>\n> **事件类型**：\n> - `'hear'`：听到说话时触发\n> - `'spawn'`：物体/单位生成时触发\"\n\n**变体示例**\n\n| 学生情况 | 调整方案 | 说明 |\n|----------|----------|------|\n| 不理解事件驱动 | 用门铃类比 | \"就像门铃，有人按了才响，不是一直响\" |\n| 忘记绑定事件 | 强调pet.on() | \"必须先用on()绑定，事件才会触发函数\" |\n| 想监听更多事件 | 介绍spawn | \"spawn事件在物品生成时触发\" |\n\n---\n\n**步骤2：闯关实践（35分钟）** `#高负荷-产出` `#IFC-即时`\n\n**教师话术**\n> \"进入关卡'边地好伙伴'！让你的宠物听到暗号后回应。然后挑战'森林加农炮'，结合循环与事件的复杂应用！\"\n\n**核心代码模式**\n\n```python\n# 示例1：听到声音后回答（Hear Event）\ndef speak(event):\n    pet.say(\"喵~\")\n\npet.on(\"hear\", speak)\nhero.say(\"你好小猫\")\n\n# 示例2：物品生成后去捡（Spawn Event）\ndef goFetch():\n    potion = hero.findNearestItem()\n    if potion:\n        pet.fetch(potion)\n\npet.on(\"spawn\", goFetch)\n```\n\n**禁忌提醒**\n❌ 忘记绑定事件——函数定义了但不会被触发\n❌ 事件类型拼写错误——'hear'不是'here'\n\n---\n\n**核心知识点**\n- 事件监听：`pet.on(\"event_type\", function_name)`\n- 事件处理函数：当事件发生时自动调用的函数\n- 事件类型：hear（听到说话）、spawn（物体生成）\n\n**教学类比**\n> 事件监听就像设置闹钟，闹钟响了（事件发生）才会叫你起床（执行函数）。\n\n`#执行层` `#测评项`\n[UID: PYAI-11-06-001]\n\n---\n\n### 1-1-7 棋逢对手\n\n#### 课程基本信息\n\n| 项目 | 内容 |\n|------|------|\n| **课程编号** | 1-1-7 |\n| **课程名称** | 棋逢对手 |\n| **认知负荷** | 高 |\n| **核心技能** | 策略制定、红蓝对抗 |\n\n#### 详细教学流程\n\n**步骤1：知识讲解（15分钟）** `#中负荷-操练` `#IFC-即时`\n\n**教师话术**\n> \"今天是激动人心的**竞技场对战**！你要用学过的所有函数知识，编写一个AI来和对手PK！\"\n>\n> \"策略制定的关键：\n> ```python\n> def choose_action():\n>     enemy = hero.findNearestEnemy()\n>     if hero.health < 50:\n>         return 'retreat'  # 血量低就撤退\n>     elif enemy and hero.distanceTo(enemy) < 10:\n>         return 'attack'   # 敌人近就攻击\n>     else:\n>         return 'advance'  # 否则前进\n> ```\n>\n> 好的策略要考虑：血量、距离、敌人数量等多种因素！\"\n\n**变体示例**\n\n| 学生情况 | 调整方案 | 说明 |\n|----------|----------|------|\n| 策略太简单 | 引导思考 | \"如果敌人很多怎么办？如果有队友呢？\" |\n| 代码太乱 | 模块化建议 | 把攻击、防御、移动分成不同函数 |\n| 想看别人策略 | 组织分享 | 让同学互相展示和学习 |\n\n---\n\n**步骤2：竞技实践（35分钟）** `#高负荷-产出` `#IFC-即时`\n\n**教师话术**\n> \"现在进入红蓝对抗！你的代码就是你的军师，帮你的英雄做出最佳决策。看谁的策略更厉害！\"\n\n**禁忌提醒**\n❌ 只攻不守——容易被反杀\n❌ 策略单一——容易被针对\n\n---\n\n**核心知识点**\n- 策略制定：根据条件选择不同行动\n- 函数综合：组合多个函数实现复杂逻辑\n- 红蓝对抗：实时对战检验代码质量\n\n**教学类比**\n> 编写AI策略就像当军师，要根据战场形势随机应变。\n\n`#执行层` `#测评项`\n[UID: PYAI-11-07-001]\n\n---\n\n### 1-1-8 量入为出\n\n#### 课程基本信息\n\n| 项目 | 内容 |\n|------|------|\n| **课程编号** | 1-1-8 |\n| **课程名称** | 量入为出 |\n| **认知负荷** | 中-高 |\n| **核心技能** | input输入、类型转换、f-string格式化 |\n\n#### 详细教学流程\n\n**步骤1：知识讲解（15分钟）** `#中负荷-操练` `#IFC-即时`\n\n**教师话术**\n> \"之前我们的程序都是'自说自话'，今天学习**人机交互**——让程序和用户对话！\"\n>\n> \"**input()函数**：获取用户输入\n> ```python\n> name = input('请输入你的名字：')\n> print(f'你好，{name}！')\n> ```\n>\n> 注意：input()返回的是**字符串**！如果要做数学运算，需要**类型转换**：\n> ```python\n> age = input('请输入你的年龄：')\n> age = int(age)  # 转换为整数\n> print(f'明年你就{age + 1}岁了！')\n> ```\"\n\n**变体示例**\n\n| 学生情况 | 调整方案 | 说明 |\n|----------|----------|------|\n| 忘记类型转换 | 演示错误 | 字符串'5' + 1会报错 |\n| f-string语法错误 | 强调格式 | f开头，变量用{}包裹 |\n| 想做更多交互 | 鼓励创意 | 可以做问答游戏、调查问卷 |\n\n---\n\n**步骤2：项目实践（35分钟）** `#高负荷-产出` `#IFC-即时`\n\n**教师话术**\n> \"现在来做一个**交互式自我介绍程序**！让程序问用户的名字、年龄、爱好，然后生成一段个性化的介绍。\"\n\n**禁忌提醒**\n❌ 忘记类型转换——数字运算出错\n❌ f-string忘记f——变量不会被替换\n\n---\n\n**核心知识点**\n- input()函数：获取用户键盘输入\n- 类型转换：int()、float()、str()\n- f-string格式化：f'文本{变量}'\n\n**教学类比**\n> input就像程序的\"耳朵\"，能听到用户说什么；print就像\"嘴巴\"，能回应用户。\n\n`#执行层` `#测评项`\n[UID: PYAI-11-08-001]\n\n---\n\n### 1-1-9 算术运算\n\n#### 课程基本信息\n\n| 项目 | 内容 |\n|------|------|\n| **课程编号** | 1-1-9 |\n| **课程名称** | 算术运算 |\n| **认知负荷** | 高 |\n| **核心技能** | 算术运算符、eval()函数 |\n\n#### 详细教学流程\n\n**步骤1：知识讲解（15分钟）** `#中负荷-操练` `#IFC-即时`\n\n**教师话术**\n> \"今天学习Python的**算术运算符**，有些你可能没见过！\"\n>\n> \"常见运算符：\n> - `+` `-` `*` `/`：加减乘除\n> - `//`：**整除**（只取整数部分）\n> - `%`：**取余**（除法的余数）\n> - `**`：**幂运算**（乘方）\n>\n> ```python\n> print(7 // 2)   # 输出: 3（整除）\n> print(7 % 2)    # 输出: 1（余数）\n> print(2 ** 3)   # 输出: 8（2的3次方）\n> ```\n>\n> 还有一个神奇的**eval()函数**，可以把字符串当代码执行：\n> ```python\n> result = eval('2 + 3 * 4')\n> print(result)  # 输出: 14\n> ```\"\n\n**变体示例**\n\n| 学生情况 | 调整方案 | 说明 |\n|----------|----------|------|\n| 混淆/和// | 对比演示 | 7/2=3.5，7//2=3 |\n| 不理解取余 | 用分糖果类比 | \"7颗糖分给2人，每人3颗，剩1颗\" |\n| 对eval好奇 | 安全提醒 | eval很强大但要小心，不要执行不信任的输入 |\n\n---\n\n**步骤2：项目实践（35分钟）** `#高负荷-产出` `#IFC-即时`\n\n**教师话术**\n> \"现在来做一个**简易计算器**！用户输入算式，程序输出结果。可以用eval()来实现，也可以自己解析算式。\"\n\n**禁忌提醒**\n❌ 除以0——ZeroDivisionError\n❌ eval执行危险代码——安全隐患\n\n---\n\n**核心知识点**\n- 整除运算符：`//`\n- 取余运算符：`%`\n- 幂运算符：`**`\n- eval()函数：执行字符串表达式\n\n**教学类比**\n> 整除就像分东西只要整数，取余就是分完剩下的。\n\n`#执行层` `#测评项`\n[UID: PYAI-11-09-001]\n\n---\n\n### 1-1-10 关系运算\n\n#### 课程基本信息\n\n| 项目 | 内容 |\n|------|------|\n| **课程编号** | 1-1-10 |\n| **课程名称** | 关系运算 |\n| **认知负荷** | 中-高 |\n| **核心技能** | 比较运算符、布尔值、变量交换 |\n\n#### 详细教学流程\n\n**步骤1：知识讲解（15分钟）** `#中负荷-操练` `#IFC-即时`\n\n**教师话术**\n> \"今天学习**关系运算符**，也叫比较运算符。它们的结果是**布尔值**：True或False。\"\n>\n> \"比较运算符：\n> - `==`：等于（注意是两个等号！）\n> - `!=`：不等于\n> - `>`、`<`：大于、小于\n> - `>=`、`<=`：大于等于、小于等于\n>\n> ```python\n> print(5 == 5)   # True\n> print(5 != 3)   # True\n> print(5 > 10)   # False\n> ```\n>\n> 还有一个经典问题：**如何交换两个变量的值？**\n> ```python\n> a, b = 10, 20\n> a, b = b, a  # Python的优雅写法\n> print(a, b)  # 输出: 20 10\n> ```\"\n\n**变体示例**\n\n| 学生情况 | 调整方案 | 说明 |\n|----------|----------|------|\n| 混淆=和== | 反复强调 | \"一个等号是赋值，两个等号是比较\" |\n| 不理解布尔值 | 用判断题类比 | \"就像判断题，对就是True，错就是False\" |\n| 变量交换不理解 | 用杯子类比 | 传统方法需要第三个杯子，Python可以直接交换 |\n\n---\n\n**步骤2：项目实践（35分钟）** `#高负荷-产出` `#IFC-即时`\n\n**教师话术**\n> \"现在来做一个**数字比较游戏**！程序生成两个随机数，用户判断它们的大小关系，程序验证答案是否正确。\"\n\n**禁忌提醒**\n❌ 用=做比较——变成赋值语句\n❌ 比较不同类型——可能得到意外结果\n\n---\n\n**核心知识点**\n- 比较运算符：==、!=、>、<、>=、<=\n- 布尔值：True和False\n- 变量交换：a, b = b, a\n\n**教学类比**\n> 比较运算就像裁判，判断两边谁大谁小，给出True或False的判决。\n\n`#执行层` `#测评项`\n[UID: PYAI-11-10-001]\n\n---\n\n### 1-1-11 碰撞检测\n\n#### 课程基本信息\n\n| 项目 | 内容 |\n|------|------|\n| **课程编号** | 1-1-11 |\n| **课程名称** | 碰撞检测 |\n| **认知负荷** | 高 |\n| **核心技能** | 碰撞原理、distanceTo、touching |\n\n#### 详细教学流程\n\n**步骤1：知识讲解（15分钟）** `#中负荷-操练` `#IFC-即时`\n\n**教师话术**\n> \"今天是本单元的最后一课，我们来学习游戏开发中超级重要的概念——**碰撞检测**！\"\n>\n> \"碰撞检测的原理：判断两个物体是否接触。\n>\n> **方法1：距离判断**\n> ```python\n> distance = hero.distanceTo(enemy)\n> if distance < 5:\n>     print('碰撞了！')\n> ```\n>\n> **方法2：touching方法**\n> ```python\n> if hero.touching(enemy):\n>     print('碰撞了！')\n> ```\n>\n> 碰撞检测在游戏中无处不在：吃金币、撞敌人、踩平台...\"\n\n**变体示例**\n\n| 学生情况 | 调整方案 | 说明 |\n|----------|----------|------|\n| 不理解距离判断 | 画图演示 | 两个圆心距离小于半径之和就碰撞 |\n| 碰撞检测不灵敏 | 调整阈值 | 距离阈值可能需要根据物体大小调整 |\n| 想做更复杂碰撞 | 介绍概念 | 矩形碰撞、像素碰撞等高级方法 |\n\n---\n\n**步骤2：项目实践（35分钟）** `#高负荷-产出` `#IFC-即时`\n\n**教师话术**\n> \"现在来做两个小项目：\n> 1. **月食模拟**：当月亮和太阳重叠时，显示'月食发生！'\n> 2. **交通避让**：控制小车躲避障碍物，碰到就游戏结束。\n>\n> 这是本单元的综合应用，用上你学过的所有知识！\"\n\n**禁忌提醒**\n❌ 碰撞阈值设太小——检测不到碰撞\n❌ 忘记持续检测——只检测一次\n\n---\n\n**核心知识点**\n- 碰撞原理：判断两物体是否接触\n- distanceTo()：计算两点距离\n- touching()：直接判断是否接触\n- 综合应用：结合函数、条件、循环\n\n**教学类比**\n> 碰撞检测就像游戏里的\"触觉\"，让程序知道物体之间有没有接触。\n\n`#执行层` `#测评项`\n[UID: PYAI-11-11-001]\n\n---\n\n## 教学禁忌清单\n\n| 序号 | 禁忌 | 原因 | 正确做法 |\n|------|------|------|----------|\n| 1 | 账号安全违规 | 影响教学活动 | 不将公用账号交给学生，不私自修改密码 |\n| 2 | 参数列表不匹配 | TypeError错误 | 实参数量必须与形参匹配（除非有默认值） |\n| 3 | 混淆`=`和`==` | 逻辑错误 | 赋值用`=`，比较用`==` |\n| 4 | 函数名不规范 | 可读性差 | 用小写字母和下划线，如attack_enemy |\n| 5 | 忘记调用函数 | 定义了但没执行 | 定义后必须调用 |\n\n`#执行层` `#测评项`\n[UID: PYAI-TABOO-11]\n\n---\n\n## 教学注意事项\n\n| 类别 | 注意事项 |\n|------|----------|\n| **形参与实参** | 反复强调形参是\"占位符\"，实参是\"具体值\" |\n| **作用域** | 函数内部定义的变量（局部）在外部无法访问 |\n| **调试技巧** | 使用print()输出变量值或函数返回值 |\n| **命名规范** | 函数名用小写字母和下划线，见名知意 |\n\n---\n\n## 底层教育学原理\n\n| 原理 | 说明 | 在本单元的应用 |\n|------|------|----------------|\n| **模块化思维** | 将复杂问题拆分为可复用模块 | 函数封装重复代码 |\n| **抽象思维** | 用参数实现泛化 | 同一函数处理不同数据 |\n| **螺旋式上升** | 知识点逐步加深 | 无参数→有参数→默认参数→多参数 |\n\n`#执行层` `#测评项`\n[UID: PYAI-THEORY-11]\n\n---\n\n**质量评估**：10/10（原子化萃取版）\n**已补充**：认知负荷标签、IFC标签、变体示例、详细教师话术\n\n---\n\n**最后更新**：2026-02-09\n"
}