{
  "title": "[STEM-3-2-06] 古代投石机",
  "source": "C:\\Users\\Frank.J\\starplanet_ai_academy\\知识库\\萃取报告\\STEM\\大班\\M2_地球与空间\\STEM-3-2-06_古代投石机.md",
  "sections": [
    {
      "title": "课程基本信息",
      "content": "| 项目 | 内容 |\n|------|------|\n| 课程编号 | STEM-3-2-06 |\n| 课程名称 | 古代投石机 |\n| 适用年龄 | 5-6岁大班 |\n| 课程时长 | 70分钟 |\n| 核心主题 | 杠杆原理、弹性势能、古代战争器械 |\n\n---"
    },
    {
      "title": "教学目标",
      "content": "- 了解古代投石机的工作原理（杠杆+弹射）\n- 探究影响投射距离的因素\n- 体验古人的工程智慧\n\n---"
    },
    {
      "title": "教学流程",
      "content": "| 环节 | 内容 |\n|------|------|\n| 引入环节 | 古代打仗没有大炮，怎么攻城？ |\n| 集体探究 | 杠杆弹射原理演示 |\n| 科学搭建 | 投石机模型 |\n| 挑战比赛 | 谁投得更远？ |\n| 历史延伸 | 古代攻城器械介绍 |\n\n---"
    },
    {
      "title": "教学技巧与话术",
      "content": "### 核心话术\n\"投石机就是一个超级大杠杆，用力拉下一头，另一头就会猛地弹起来，把石头甩出去。\"\n\n### 物理解释\n\"勺子的长短、用多大力气拉、石头的重量都会影响能飞多远。\"\n\n---"
    },
    {
      "title": "搭建步骤",
      "content": "1. **Step 1**：搭建稳固底座\n2. **Step 2**：安装支撑架和转轴\n3. **Step 3**：制作长臂杠杆\n4. **Step 4**：在短臂端添加配重或弹力装置\n5. **Step 5**：在长臂端安装投石勺\n6. **Step 6**：测试并调整\n\n---"
    },
    {
      "title": "禁忌与安全警告",
      "content": "- 投射方向要远离人群\n- 使用软质\"石头\"（如海绵球）进行测试\n- 释放时不要站在投石机前方\n\n---"
    },
    {
      "title": "IFC即时反馈点",
      "content": "| 问题 | 解决方案 |\n|------|---------|\n| 投不远 | 检查杠杆比例和配重 |\n| 方向不稳 | 检查转轴是否松动 |\n\n---"
    },
    {
      "title": "教育理论",
      "content": "- **物理应用**：杠杆原理与弹性势能\n- **历史文化**：古代工程智慧\n\n---\n\n[上一课](STEM-3-2-05_太阳能应用.md) | [模块概览](_模块概览.md) | [下一课](STEM-3-2-07_指南针与导航.md)"
    }
  ],
  "full_content": "# [STEM-3-2-06] 古代投石机\n\n> **模块**：大班M2 地球与空间\n> **认知负荷**：中高\n> **核心技能**：杠杆原理、弹性势能、古代战争器械\n> **UID**：STEM-B2-06-001\n\n---\n\n## 课程基本信息\n\n| 项目 | 内容 |\n|------|------|\n| 课程编号 | STEM-3-2-06 |\n| 课程名称 | 古代投石机 |\n| 适用年龄 | 5-6岁大班 |\n| 课程时长 | 70分钟 |\n| 核心主题 | 杠杆原理、弹性势能、古代战争器械 |\n\n---\n\n## 教学目标\n\n- 了解古代投石机的工作原理（杠杆+弹射）\n- 探究影响投射距离的因素\n- 体验古人的工程智慧\n\n---\n\n## 教学流程\n\n| 环节 | 内容 |\n|------|------|\n| 引入环节 | 古代打仗没有大炮，怎么攻城？ |\n| 集体探究 | 杠杆弹射原理演示 |\n| 科学搭建 | 投石机模型 |\n| 挑战比赛 | 谁投得更远？ |\n| 历史延伸 | 古代攻城器械介绍 |\n\n---\n\n## 教学技巧与话术\n\n### 核心话术\n\"投石机就是一个超级大杠杆，用力拉下一头，另一头就会猛地弹起来，把石头甩出去。\"\n\n### 物理解释\n\"勺子的长短、用多大力气拉、石头的重量都会影响能飞多远。\"\n\n---\n\n## 搭建步骤\n\n1. **Step 1**：搭建稳固底座\n2. **Step 2**：安装支撑架和转轴\n3. **Step 3**：制作长臂杠杆\n4. **Step 4**：在短臂端添加配重或弹力装置\n5. **Step 5**：在长臂端安装投石勺\n6. **Step 6**：测试并调整\n\n---\n\n## 禁忌与安全警告\n\n- 投射方向要远离人群\n- 使用软质\"石头\"（如海绵球）进行测试\n- 释放时不要站在投石机前方\n\n---\n\n## IFC即时反馈点\n\n| 问题 | 解决方案 |\n|------|---------|\n| 投不远 | 检查杠杆比例和配重 |\n| 方向不稳 | 检查转轴是否松动 |\n\n---\n\n## 教育理论\n\n- **物理应用**：杠杆原理与弹性势能\n- **历史文化**：古代工程智慧\n\n---\n\n[上一课](STEM-3-2-05_太阳能应用.md) | [模块概览](_模块概览.md) | [下一课](STEM-3-2-07_指南针与导航.md)\n"
}