{
  "title": "STEM大班 M4 智能硬件 模块概览",
  "source": "C:\\Users\\Frank.J\\starplanet_ai_academy\\知识库\\萃取报告\\STEM\\大班\\M4_智能硬件\\_模块概览.md",
  "sections": [
    {
      "title": "课程列表",
      "content": "| 编号 | 课程名称 | 核心技能 | 文件 |\n|------|---------|---------|------|\n| STEM-3-4-01 | 智能风扇 | 温度传感器、条件判断 | [链接](STEM-3-4-01_智能风扇.md) |\n| STEM-3-4-02 | 智能路灯 | 光线传感器、自动控制 | [链接](STEM-3-4-02_智能路灯.md) |\n| STEM-3-4-03 | 避障小车 | 距离传感器、自动避障 | [链接](STEM-3-4-03_避障小车.md) |\n| STEM-3-4-04 | 巡线小车 | 颜色传感器、循迹控制 | [链接](STEM-3-4-04_巡线小车.md) |\n| STEM-3-4-05 | 遥控机械臂 | 舵机控制、多自由度 | [链接](STEM-3-4-05_遥控机械臂.md) |\n| STEM-3-4-06 | 智能垃圾桶 | 人体感应、序列编程 | [链接](STEM-3-4-06_智能垃圾桶.md) |\n| STEM-3-4-07 | 防近视支架 | 距离传感器、健康应用 | [链接](STEM-3-4-07_防近视支架.md) |\n| STEM-3-4-08 | 尤克里里 | 传感器映射、电子乐器 | [链接](STEM-3-4-08_尤克里里.md) |\n| STEM-3-4-09 | 疯狂娃娃机 | 二维运动、摇杆控制 | [链接](STEM-3-4-09_疯狂娃娃机.md) |\n| STEM-3-4-10 | 智能储蓄罐 | 计数变量、自动化机械 | [链接](STEM-3-4-10_智能储蓄罐.md) |\n| STEM-3-4-11 | 数字密码锁 | 逻辑组合、顺序结构 | [链接](STEM-3-4-11_数字密码锁.md) |\n| STEM-3-4-12 | 自动售卖机 | IPO模型、综合应用 | [链接](STEM-3-4-12_自动售卖机.md) |\n\n---"
    },
    {
      "title": "核心知识点覆盖",
      "content": "### 传感器类型\n- 温度传感器\n- 光线传感器\n- 距离传感器（红外/超声波）\n- 颜色/灰度传感器\n- 人体感应传感器\n\n### 执行器类型\n- 电机（直流电机）\n- 舵机（角度控制）\n- LED灯\n- 蜂鸣器\n\n### 编程逻辑\n- 条件判断（If...Then...Else）\n- 循环结构（Loop）\n- 变量使用（Variable）\n- 顺序执行（Sequence）\n\n### 机械结构\n- 齿轮传动\n- 连杆机构\n- 螺旋推进\n- 龙门架结构\n\n---"
    },
    {
      "title": "能力培养目标",
      "content": "1. **计算思维** - 通过编程逻辑培养\n2. **工程设计能力** - 通过搭建实践培养\n3. **问题解决能力** - 通过调试优化培养\n4. **创新创造意识** - 通过项目拓展培养\n\n---"
    },
    {
      "title": "导航",
      "content": "- [返回大班课程](../_索引.md)\n- [返回STEM总索引](../../_索引.md)\n\n---\n\n*萃取时间：2026-02-05*\n*拆分时间：2026-02-10*"
    }
  ],
  "full_content": "# STEM大班 M4 智能硬件 模块概览\n\n> **适用年龄**：5-6岁大班\n> **课程数量**：12节\n> **核心主题**：智能硬件与编程控制\n> **教学目标**：通过传感器、电机和编程，让幼儿体验智能设备的工作原理\n\n---\n\n## 课程列表\n\n| 编号 | 课程名称 | 核心技能 | 文件 |\n|------|---------|---------|------|\n| STEM-3-4-01 | 智能风扇 | 温度传感器、条件判断 | [链接](STEM-3-4-01_智能风扇.md) |\n| STEM-3-4-02 | 智能路灯 | 光线传感器、自动控制 | [链接](STEM-3-4-02_智能路灯.md) |\n| STEM-3-4-03 | 避障小车 | 距离传感器、自动避障 | [链接](STEM-3-4-03_避障小车.md) |\n| STEM-3-4-04 | 巡线小车 | 颜色传感器、循迹控制 | [链接](STEM-3-4-04_巡线小车.md) |\n| STEM-3-4-05 | 遥控机械臂 | 舵机控制、多自由度 | [链接](STEM-3-4-05_遥控机械臂.md) |\n| STEM-3-4-06 | 智能垃圾桶 | 人体感应、序列编程 | [链接](STEM-3-4-06_智能垃圾桶.md) |\n| STEM-3-4-07 | 防近视支架 | 距离传感器、健康应用 | [链接](STEM-3-4-07_防近视支架.md) |\n| STEM-3-4-08 | 尤克里里 | 传感器映射、电子乐器 | [链接](STEM-3-4-08_尤克里里.md) |\n| STEM-3-4-09 | 疯狂娃娃机 | 二维运动、摇杆控制 | [链接](STEM-3-4-09_疯狂娃娃机.md) |\n| STEM-3-4-10 | 智能储蓄罐 | 计数变量、自动化机械 | [链接](STEM-3-4-10_智能储蓄罐.md) |\n| STEM-3-4-11 | 数字密码锁 | 逻辑组合、顺序结构 | [链接](STEM-3-4-11_数字密码锁.md) |\n| STEM-3-4-12 | 自动售卖机 | IPO模型、综合应用 | [链接](STEM-3-4-12_自动售卖机.md) |\n\n---\n\n## 核心知识点覆盖\n\n### 传感器类型\n- 温度传感器\n- 光线传感器\n- 距离传感器（红外/超声波）\n- 颜色/灰度传感器\n- 人体感应传感器\n\n### 执行器类型\n- 电机（直流电机）\n- 舵机（角度控制）\n- LED灯\n- 蜂鸣器\n\n### 编程逻辑\n- 条件判断（If...Then...Else）\n- 循环结构（Loop）\n- 变量使用（Variable）\n- 顺序执行（Sequence）\n\n### 机械结构\n- 齿轮传动\n- 连杆机构\n- 螺旋推进\n- 龙门架结构\n\n---\n\n## 能力培养目标\n\n1. **计算思维** - 通过编程逻辑培养\n2. **工程设计能力** - 通过搭建实践培养\n3. **问题解决能力** - 通过调试优化培养\n4. **创新创造意识** - 通过项目拓展培养\n\n---\n\n## 导航\n\n- [返回大班课程](../_索引.md)\n- [返回STEM总索引](../../_索引.md)\n\n---\n\n*萃取时间：2026-02-05*\n*拆分时间：2026-02-10*\n"
}