{
  "title": "STEM素材资源库",
  "source": "C:\\Users\\Frank.J\\starplanet_ai_academy\\知识库\\萃取报告\\素材_STEM素材资源库_V1.md",
  "sections": [
    {
      "title": "一、素材分类概览",
      "content": "STEM素材库是斯坦星球教学体系的重要支撑，包含课程内容、硬件教具、教学方法论、评价体系和数字化平台五大类素材，形成完整的教学闭环。\n\n### 1.1 素材类型统计\n\n| 素材类型 | 主要内容 | 用途 |\n|----------|----------|------|\n| 课程内容素材 | STEM 0-3阶段课程、编程课程 | 教学实施 |\n| 硬件教具素材 | 1600+种自研教具 | 动手实践 |\n| 方法论素材 | 5E教学法、PBL项目制 | 教学指导 |\n| 评价体系素材 | 八大能力模型、咨询SOP | 效果评估 |\n| 数字化平台 | 一站式编程平台、AI老师 | 线上支持 |\n\n---"
    },
    {
      "title": "二、核心课程内容素材",
      "content": "### 2.1 STEM幼儿科创课程（2.5-6岁）\n\n该体系强调跨学科整合，包含**1000+科学实验**和**1280+知识点**。\n\n#### STEM 0（2.5-3岁）- 科学启蒙\n- 建立常识认知\n- 感官探索为主\n\n#### STEM 1（3-4岁）- \"动手小天才\"\n\n| 主题模块 | 核心内容 | 配套素材 |\n|----------|----------|----------|\n| 人体认知 | 指纹、五官 | 骨骼拼图、听诊器 |\n| 动物世界 | 恐龙化石挖掘 | 化石挖掘套装 |\n| 自然植物 | 叶脉拓印 | 植物标本工具 |\n| 空间认知 | 方位、形状 | 昆虫观察盒 |\n\n#### STEM 2（4-5岁）- \"玩转工程感知科学\"\n\n| 主题模块 | 核心内容 | 配套素材 |\n|----------|----------|----------|\n| 交通工具 | F1赛车、潜水艇 | \"百变工程\"积木 |\n| 建筑结构 | 拱桥、金字塔 | 磁力片 |\n| 物理现象 | 声光电 | 电路实验套装 |\n| 实体编程 | 无屏编程入门 | CodeMaker实体编程积木 |\n\n#### STEM 3（5-6岁）- \"机械结构原理解析\"\n\n| 主题模块 | 核心内容 | 配套素材 |\n|----------|----------|----------|\n| 机械传动 | 齿轮、杠杆、滑轮 | 齿轮组、涡轮蜗杆装置 |\n| 能源科学 | 太阳能、风能 | 能源实验套装 |\n| 逻辑编程 | 与/或/非逻辑 | 电路模块、传感器模块 |\n\n### 2.2 编程与人工智能课程（6岁+）\n\n**进阶路径：**\n```\nScratch图形化 → Python代码 → C++信奥\n```\n\n**PBL认知模型：**\n- 点（数据）→ 线（算法）→ 面（结构）→ 体（系统）\n\n---"
    },
    {
      "title": "三、研发硬件与教具素材",
      "content": "斯坦星球拥有强大的研发实力，建立了**北美研发中心**及**\"星球智库\"**，自主研发了**1600+种**教具。\n\n### 3.1 核心硬件产品\n\n#### CircleBit创客开发板\n- **特点**：独家研发的\"中国芯\"\n- **板载元件**：\n  - 6轴陀螺仪\n  - 光线传感器\n  - 温湿度传感器\n  - OLED显示屏\n  - 全彩LED\n  - 十几种元件\n- **支持**：图形化及代码编程\n\n#### ScratchStar硬件套装\n- 结合乐高积木与电子元件\n- 实现\"软硬结合\"教学\n- 支持WeDo 2.0兼容\n\n#### Python AI硬件箱\n| 组件 | 功能 |\n|------|------|\n| 摄像头 | 人脸/颜色识别 |\n| 麦克风 | 语音交互 |\n| 高阶传感器 | 智能家居、自动驾驶项目 |\n\n### 3.2 情景化动画课件\n\n- **名称**：《斯坦星球历险记》\n- **投资**：斥资千万研发\n- **IP角色**：\n  - 机器人小白\n  - 罗宾博士\n- **作用**：将科学实验任务视觉化、故事化\n\n---"
    },
    {
      "title": "四、教学方法论素材",
      "content": "### 4.1 5E探究式教学法\n\n| 步骤 | 英文 | 内容 | 示例 |\n|------|------|------|------|\n| 1 | Engagement | 动画引入，激发好奇 | \"恐龙去哪了\" |\n| 2 | Exploration | 动手实验，假设验证 | \"模拟火山喷发\" |\n| 3 | Explanation | 归纳现象，逻辑表达 | 学生讲解发现 |\n| 4 | Extension | 跨学科应用，模型搭建 | 延伸项目 |\n| 5 | Evaluation | 反思调整，多元评估 | 作品展示 |\n\n### 4.2 PBL项目制学习\n\n**核心理念**：\n- \"为理解而教，为创新而学\"\n- 通过制作真实作品整合知识\n\n**典型项目**：\n- 智能感应灯\n- 复刻经典游戏\n\n**培养的隐性能力**：\n- 挫折商（AQ）\n- 调试精神（Debug）\n\n---"
    },
    {
      "title": "五、评价与规划体系素材",
      "content": "### 5.1 八大能力模型\n\n| 能力 | 说明 |\n|------|------|\n| 观察力 | 细致观察事物的能力 |\n| 分析力 | 分解问题的能力 |\n| 理解力 | 深入理解概念的能力 |\n| 想象力 | 创造性思维能力 |\n| 判断力 | 做出正确判断的能力 |\n| 推理力 | 逻辑推理能力 |\n| 动手能力 | 实践操作能力 |\n| 语言能力 | 表达沟通能力 |\n\n> 这是测评和教学的标尺\n\n### 5.2 咨询转化话术SOP\n\n**核心公式**：\n```\n现象(Phenomenon) → 做法(Method) → 能力(Ability) → 好处(Benefit)\n```\n\n**经典理论**：\n- **游泳理论**：知识vs能力的区别\n- **考试本质论**：语数外考的本质是思维能力\n\n### 5.3 学员规划SOP\n\n#### 画像构建\n基于以下维度建立学员档案：\n- 性别\n- 课时\n- 优劣势（如\"动手强但逻辑弱\"）\n\n#### 双版本规划\n\n| 版本 | 特点 | 适用人群 |\n|------|------|----------|\n| 考级版 | 高要求、走白名单赛事 | 有升学需求的学员 |\n| 兴趣版 | 低要求、兴趣培养 | 以兴趣为主的学员 |\n\n#### 赛事出口规划\n\n| 赛事 | 类型 | 参与时机 |\n|------|------|----------|\n| 蓝桥杯 | 编程 | 按规划时间点 |\n| NOC | 综合 | 按规划时间点 |\n| VEX | 机器人 | 按规划时间点 |\n| Botball | 机器人 | 按规划时间点 |\n\n---"
    },
    {
      "title": "六、数字化平台素材",
      "content": "### 6.1 一站式编程平台\n\n**功能集成**：\n- 创作工具\n- 考级题库\n- 信奥OJ系统\n- Scratch/Python/C++代码互转\n\n### 6.2 AI老师\n\n**功能**：\n- 辅助学生进行编程自学\n- 知识点回顾\n- 智能答疑\n\n---"
    },
    {
      "title": "七、素材体系闭环",
      "content": "```\n情景化动画（吸引兴趣）\n        ↓\n自研硬件 + 5E/PBL教学法（落实知识与能力）\n        ↓\n八大能力测评（量化效果）\n        ↓\nSOP话术 + 赛事规划（转化为满意度和续费）\n```\n\n---"
    },
    {
      "title": "八、与课程体系的对应关系",
      "content": "| 素材类型 | 对应课程 | 使用场景 |\n|----------|----------|----------|\n| STEM 1素材 | 小班课程 | 3-4岁教学 |\n| STEM 2素材 | 中班课程 | 4-5岁教学 |\n| STEM 3素材 | 大班课程 | 5-6岁教学 |\n| CircleBit | CODE课程 | 软硬结合教学 |\n| Python AI硬件箱 | Python课程 | AI项目实践 |\n| 5E教学法 | 全阶段 | 教学流程指导 |\n| 八大能力模型 | 全阶段 | 学员评估 |\n\n---"
    },
    {
      "title": "九、标签",
      "content": "```\n#素材 #STEM #教具 #5E教学法 #PBL #八大能力 #CircleBit #硬件 #评价体系 #咨询SOP\n```\n\n---\n\n**文档维护者**：知识库管理员\n**最后更新**：2026-02-02"
    }
  ],
  "full_content": "# STEM素材资源库\n\n> **文档类型**：知识块 - 素材资源\n> **来源**：NotebookLM STEM Materials (20个来源文件)\n> **萃取日期**：2026-02-02\n> **版本**：V1.0\n\n---\n\n## 一、素材分类概览\n\nSTEM素材库是斯坦星球教学体系的重要支撑，包含课程内容、硬件教具、教学方法论、评价体系和数字化平台五大类素材，形成完整的教学闭环。\n\n### 1.1 素材类型统计\n\n| 素材类型 | 主要内容 | 用途 |\n|----------|----------|------|\n| 课程内容素材 | STEM 0-3阶段课程、编程课程 | 教学实施 |\n| 硬件教具素材 | 1600+种自研教具 | 动手实践 |\n| 方法论素材 | 5E教学法、PBL项目制 | 教学指导 |\n| 评价体系素材 | 八大能力模型、咨询SOP | 效果评估 |\n| 数字化平台 | 一站式编程平台、AI老师 | 线上支持 |\n\n---\n\n## 二、核心课程内容素材\n\n### 2.1 STEM幼儿科创课程（2.5-6岁）\n\n该体系强调跨学科整合，包含**1000+科学实验**和**1280+知识点**。\n\n#### STEM 0（2.5-3岁）- 科学启蒙\n- 建立常识认知\n- 感官探索为主\n\n#### STEM 1（3-4岁）- \"动手小天才\"\n\n| 主题模块 | 核心内容 | 配套素材 |\n|----------|----------|----------|\n| 人体认知 | 指纹、五官 | 骨骼拼图、听诊器 |\n| 动物世界 | 恐龙化石挖掘 | 化石挖掘套装 |\n| 自然植物 | 叶脉拓印 | 植物标本工具 |\n| 空间认知 | 方位、形状 | 昆虫观察盒 |\n\n#### STEM 2（4-5岁）- \"玩转工程感知科学\"\n\n| 主题模块 | 核心内容 | 配套素材 |\n|----------|----------|----------|\n| 交通工具 | F1赛车、潜水艇 | \"百变工程\"积木 |\n| 建筑结构 | 拱桥、金字塔 | 磁力片 |\n| 物理现象 | 声光电 | 电路实验套装 |\n| 实体编程 | 无屏编程入门 | CodeMaker实体编程积木 |\n\n#### STEM 3（5-6岁）- \"机械结构原理解析\"\n\n| 主题模块 | 核心内容 | 配套素材 |\n|----------|----------|----------|\n| 机械传动 | 齿轮、杠杆、滑轮 | 齿轮组、涡轮蜗杆装置 |\n| 能源科学 | 太阳能、风能 | 能源实验套装 |\n| 逻辑编程 | 与/或/非逻辑 | 电路模块、传感器模块 |\n\n### 2.2 编程与人工智能课程（6岁+）\n\n**进阶路径：**\n```\nScratch图形化 → Python代码 → C++信奥\n```\n\n**PBL认知模型：**\n- 点（数据）→ 线（算法）→ 面（结构）→ 体（系统）\n\n---\n\n## 三、研发硬件与教具素材\n\n斯坦星球拥有强大的研发实力，建立了**北美研发中心**及**\"星球智库\"**，自主研发了**1600+种**教具。\n\n### 3.1 核心硬件产品\n\n#### CircleBit创客开发板\n- **特点**：独家研发的\"中国芯\"\n- **板载元件**：\n  - 6轴陀螺仪\n  - 光线传感器\n  - 温湿度传感器\n  - OLED显示屏\n  - 全彩LED\n  - 十几种元件\n- **支持**：图形化及代码编程\n\n#### ScratchStar硬件套装\n- 结合乐高积木与电子元件\n- 实现\"软硬结合\"教学\n- 支持WeDo 2.0兼容\n\n#### Python AI硬件箱\n| 组件 | 功能 |\n|------|------|\n| 摄像头 | 人脸/颜色识别 |\n| 麦克风 | 语音交互 |\n| 高阶传感器 | 智能家居、自动驾驶项目 |\n\n### 3.2 情景化动画课件\n\n- **名称**：《斯坦星球历险记》\n- **投资**：斥资千万研发\n- **IP角色**：\n  - 机器人小白\n  - 罗宾博士\n- **作用**：将科学实验任务视觉化、故事化\n\n---\n\n## 四、教学方法论素材\n\n### 4.1 5E探究式教学法\n\n| 步骤 | 英文 | 内容 | 示例 |\n|------|------|------|------|\n| 1 | Engagement | 动画引入，激发好奇 | \"恐龙去哪了\" |\n| 2 | Exploration | 动手实验，假设验证 | \"模拟火山喷发\" |\n| 3 | Explanation | 归纳现象，逻辑表达 | 学生讲解发现 |\n| 4 | Extension | 跨学科应用，模型搭建 | 延伸项目 |\n| 5 | Evaluation | 反思调整，多元评估 | 作品展示 |\n\n### 4.2 PBL项目制学习\n\n**核心理念**：\n- \"为理解而教，为创新而学\"\n- 通过制作真实作品整合知识\n\n**典型项目**：\n- 智能感应灯\n- 复刻经典游戏\n\n**培养的隐性能力**：\n- 挫折商（AQ）\n- 调试精神（Debug）\n\n---\n\n## 五、评价与规划体系素材\n\n### 5.1 八大能力模型\n\n| 能力 | 说明 |\n|------|------|\n| 观察力 | 细致观察事物的能力 |\n| 分析力 | 分解问题的能力 |\n| 理解力 | 深入理解概念的能力 |\n| 想象力 | 创造性思维能力 |\n| 判断力 | 做出正确判断的能力 |\n| 推理力 | 逻辑推理能力 |\n| 动手能力 | 实践操作能力 |\n| 语言能力 | 表达沟通能力 |\n\n> 这是测评和教学的标尺\n\n### 5.2 咨询转化话术SOP\n\n**核心公式**：\n```\n现象(Phenomenon) → 做法(Method) → 能力(Ability) → 好处(Benefit)\n```\n\n**经典理论**：\n- **游泳理论**：知识vs能力的区别\n- **考试本质论**：语数外考的本质是思维能力\n\n### 5.3 学员规划SOP\n\n#### 画像构建\n基于以下维度建立学员档案：\n- 性别\n- 课时\n- 优劣势（如\"动手强但逻辑弱\"）\n\n#### 双版本规划\n\n| 版本 | 特点 | 适用人群 |\n|------|------|----------|\n| 考级版 | 高要求、走白名单赛事 | 有升学需求的学员 |\n| 兴趣版 | 低要求、兴趣培养 | 以兴趣为主的学员 |\n\n#### 赛事出口规划\n\n| 赛事 | 类型 | 参与时机 |\n|------|------|----------|\n| 蓝桥杯 | 编程 | 按规划时间点 |\n| NOC | 综合 | 按规划时间点 |\n| VEX | 机器人 | 按规划时间点 |\n| Botball | 机器人 | 按规划时间点 |\n\n---\n\n## 六、数字化平台素材\n\n### 6.1 一站式编程平台\n\n**功能集成**：\n- 创作工具\n- 考级题库\n- 信奥OJ系统\n- Scratch/Python/C++代码互转\n\n### 6.2 AI老师\n\n**功能**：\n- 辅助学生进行编程自学\n- 知识点回顾\n- 智能答疑\n\n---\n\n## 七、素材体系闭环\n\n```\n情景化动画（吸引兴趣）\n        ↓\n自研硬件 + 5E/PBL教学法（落实知识与能力）\n        ↓\n八大能力测评（量化效果）\n        ↓\nSOP话术 + 赛事规划（转化为满意度和续费）\n```\n\n---\n\n## 八、与课程体系的对应关系\n\n| 素材类型 | 对应课程 | 使用场景 |\n|----------|----------|----------|\n| STEM 1素材 | 小班课程 | 3-4岁教学 |\n| STEM 2素材 | 中班课程 | 4-5岁教学 |\n| STEM 3素材 | 大班课程 | 5-6岁教学 |\n| CircleBit | CODE课程 | 软硬结合教学 |\n| Python AI硬件箱 | Python课程 | AI项目实践 |\n| 5E教学法 | 全阶段 | 教学流程指导 |\n| 八大能力模型 | 全阶段 | 学员评估 |\n\n---\n\n## 九、标签\n\n```\n#素材 #STEM #教具 #5E教学法 #PBL #八大能力 #CircleBit #硬件 #评价体系 #咨询SOP\n```\n\n---\n\n**文档维护者**：知识库管理员\n**最后更新**：2026-02-02\n"
}